setup.py
prob_dist_gauss_binom/Binomialdistribution.py
prob_dist_gauss_binom/Gaussiandistribution.py
prob_dist_gauss_binom/Generaldistribution.py
prob_dist_gauss_binom/__init__.py
prob_dist_gauss_binom.egg-info/PKG-INFO
prob_dist_gauss_binom.egg-info/SOURCES.txt
prob_dist_gauss_binom.egg-info/dependency_links.txt
prob_dist_gauss_binom.egg-info/not-zip-safe
prob_dist_gauss_binom.egg-info/top_level.txt