Metadata-Version: 1.0
Name: prob-dist-gauss-binom
Version: 0.1
Summary: Gaussian and Binomial distributions
Home-page: UNKNOWN
Author: Mohamed ElMesawy
Author-email: mohamedelmesawy1993@gmail.com
License: UNKNOWN
Platform: UNKNOWN
